stac_table.py
stac_table-1.0.0.dist-info/WHEEL
stac_table-1.0.0.dist-info/METADATA
stac_table-1.0.0.dist-info/RECORD
